is_that_you/__main__.py
is_that_you-0.0.2.dist-info/METADATA
is_that_you-0.0.2.dist-info/WHEEL
is_that_you-0.0.2.dist-info/RECORD
