Metadata-Version: 2.1
Name: is_that_you
Version: 0.0.2
Summary: A vtuber program with emotion recognition
Project-URL: Homepage, https://github.com/megahomyak/is_that_you
Author-email: megahomyak <g.megahomyak@gmail.com>
Requires-Python: >=3.8
Requires-Dist: fer==22.5.1
Requires-Dist: numpy==1.22.0
Requires-Dist: opencv-python==4.8.1.78
Requires-Dist: pillow<11.0.0,>=10.1.0
Requires-Dist: pyvirtualcam==0.9.1
Requires-Dist: sounddevice<0.5.0,>=0.4.6
Requires-Dist: tensorflow>=1.7
